{
  "$schema": "https://mintlify.com/docs.json",
  "theme": "mint",
  "name": "Mint Starter Kit",
  "colors": {
    "primary": "#16A34A",
    "light": "#07C983",
    "dark": "#15803D"
  },
  "favicon": "/logo/favicon.png",
  "navigation": {
    "tabs": [
      {
        "tab": "Guide",
        "groups": [
          {
            "group": "Introduction",
            "pages": [
              "Introduction/WelcometoMysamantha"
            ]
          },
          {
            "group": "How it works",
            "pages": [
              "Howitworks/HowMysamanthaWorks"
            ]
          },
          {
            "group": "Core Features",
            "pages": [
              "CoreFeatures/Notes",
              "CoreFeatures/ToDo",
              "CoreFeatures/Journal",
              "CoreFeatures/Assistant"
            ]
          },
          {
            "group": "Integrations",
            "pages": [
              "Integrations/Email",
              "Integrations/Calendar",
              "Integrations/Gmap"
            ]
          }
        ]
      }
    ]
  },
  "logo": {
    "light": "/logo/Black Logo (5).svg",
    "dark": "/logo/White Logo (5).svg"
  },
  "navbar": {
    "links": [
      {
        "label": "Support",
        "href": "mailto:samantha@zemuria.com"
      },
      {
        "label": "Blog",
        "href": "https://mysamantha.ai/blog"
      }
    ],
    "primary": {
      "type": "button",
      "label": "Dashboard",
      "href": "https://mysamantha.ai"
    }
  },
  "contextual": {
    "options": [
      "copy"
    ]
  },
  "footer": {
    "socials": {
      "x": "https://x.com/samanthareplies",
      "instagram": "https://www.instagram.com/samanthareplies/",
      "telegram": "https://t.me/samanthareplies"
    }
  }
}